README.md
setup.py
ovirt_python_sdk/__init__.py
ovirt_python_sdk/api.py
ovirt_python_sdk/exceptions.py
ovirt_python_sdk/utils.py
ovirt_python_sdk.egg-info/PKG-INFO
ovirt_python_sdk.egg-info/SOURCES.txt
ovirt_python_sdk.egg-info/dependency_links.txt
ovirt_python_sdk.egg-info/requires.txt
ovirt_python_sdk.egg-info/top_level.txt