Metadata-Version: 1.0
Name: ovirt-python-sdk
Version: 1.2.0
Summary: Ovirt Python SDK
Home-page: https://github.com/gamehost/ovirt_python_sdk
Author: Toliak, Underlor
Author-email: cfyz_74@mail.ru
License: Creative Commons Attribution-Noncommercial-Share Alike license
Platform: UNKNOWN
